tlfi/__init__.py
tlfi/__main__.py
tlfi-0.0.3.dist-info/METADATA
tlfi-0.0.3.dist-info/WHEEL
tlfi-0.0.3.dist-info/entry_points.txt
tlfi-0.0.3.dist-info/top_level.txt
tlfi-0.0.3.dist-info/RECORD
